l0n0lnet/__init__.py
l0n0lnet/buildcpp.py
l0n0lnet/commands.py
l0n0lnet/confuse_tcp.py
l0n0lnet/http_tunnel_server.py
l0n0lnet/libse_windows_x64.py
l0n0lnet/libse_windows_x86.py
l0n0lnet/reverse.py
l0n0lnet/socks.py
l0n0lnet/stream_parser.py
l0n0lnet/tcp.py
l0n0lnet/transform.py
l0n0lnet/udp.py
l0n0lnet/utils.py
l0n0lnet-2.7.1.dist-info/LICENSE
l0n0lnet-2.7.1.dist-info/METADATA
l0n0lnet-2.7.1.dist-info/WHEEL
l0n0lnet-2.7.1.dist-info/entry_points.txt
l0n0lnet-2.7.1.dist-info/top_level.txt
l0n0lnet-2.7.1.dist-info/RECORD
