Metadata-Version: 2.1
Name: l0n0lnet
Version: 2.7.1
Summary: 一个简单的高性能c++网络库
Home-page: https://gitee.com/l00n00l/l0n0lnet
Author: l0n0l
Author-email: 1038352856@qq.com
License: UNKNOWN
Platform: UNKNOWN
Classifier: Programming Language :: Python :: 3
Classifier: License :: OSI Approved :: MIT License
Classifier: Operating System :: OS Independent
Requires-Python: >=3.6
Requires-Dist: cmake
Requires-Dist: GitPython
